backend.v
//File Name: BACKNED
// Type: Module
// Department : Electrical engineering
// Author: Sagar
//Author's Email ID: guptasagar19965@gmail.com
// Purpose:TEST
// Operation : TEST
// Date : 10 July 2023
// BACKEND DESIGN //
module backend( i_resetbAll,
		i_clk,
		i_sclk,
		i_sdin,
		i_vco_clk,
		o_ready,
		o_resetb1,
		o_gainA1,
		o_resetb2,
		o_gainA2,
		o_resetbvco,);
// INPUT OUTPUT REGISTERS DECLARATION //
    input i_resetbAll, i_clk, i_sclk, i_sdin, i_vco_clk;
	reg [4:0]data;
	integer i;
    output reg o_ready, o_resetb1, o_resetb2, o_resetbvco;
    output reg [1:0] o_gainA1;
    output reg [2:0] o_gainA2;
    reg [4:0] shiftreg;
    reg [4:0] shift2;
    reg [2:0] count; 
    //take serial data from i_sdin and read the data using shift register
    always @ ( posedge (i_sclk))
	
		  begin
					shift2= shiftreg>>1;
					shiftreg ={i_sdin, shift2[3:0]};
					count<=count+1;
			if (count==4)
				begin				
					o_gainA1[0]	<=	shiftreg[0];
					o_gainA1[1]	<=	shiftreg[1];
					o_gainA2[0]	<=	shiftreg[2];
					o_gainA2[1]	<=	shiftreg[3];
					o_gainA2[2]	<=	shiftreg[4];
				end
 
		   end	
	always@(posedge (i_clk) or negedge(i_resetbAll))
	begin
      if(i_resetbAll)  //when i_resetbAll=1, the starup sequence in initiated
	     begin
                for(i=0;i<5;i=i+1)         // store data in reg data 
	              begin
	                 @(posedge i_sclk);
		              data <= {data[4:1],i_sdin};
		          end
               repeat(2)                  // now we wait for two clock cycles
	             begin
		          @(posedge (i_clk) or negedge(i_resetbAll)) ;
	             end
	           o_resetbvco <=1;   // set o_resetbvco=1
	           repeat(10)        // wait for 10 clock cycles
	             begin
		           @(posedge (i_clk) or negedge(i_resetbAll)) ;
	              end
	            o_resetb1 <=1;// set o_resetb1=1
	            o_resetb2<=1;// set o_resetb2=1
	           repeat(10)    // wait for 10 clock cycles
	             begin
		           @(posedge (i_clk) or negedge(i_resetbAll)) ;
	             end
	            o_ready<=1;    // set o_ready=1
		 end
        else           // when  i_resetbAll=0 all  outputs of the backend should be pulled to zero
		  begin
           o_ready <= 0;
           o_resetb1 <= 0;
           o_resetb2 <= 0;
           o_resetbvco <= 0;
           o_gainA1[0] <= 0;
           o_gainA1[1] <= 0;
           o_gainA2[0] <= 0;
           o_gainA2[1] <= 0;
           o_gainA2[2] <= 0;
           shiftreg <=0;
	       shift2 <= 0;
           count <= 0;
           data <=0;
		   end
	end
//====================================================================================
endmodule

FPGA_model.v
//File Name: FPGA 
// Type: Module
// Department : Electrical engineering
// Author: Sagar
//Author's Email ID: guptasagar19965@gmail.com
// Purpose: Module
// Operation : data control
// Date : 10 July 2023
///////////////////////////////////////////////////////////////////////////////
/*FPGA model
 * Generates reset signal for the chip
 * Sends out progamming bits to the chip
*/
module FPGA_model(	i_resetbFPGA,
			i_ready,
			i_mainclk,
			o_resetbAll,
			o_sclk, 
			o_sdout);

//============================================================================
//Parameter declarations
parameter opcode_gainA1	= 1; //range: 0-3. Gain for amplifier 1
parameter opcode_gainA2	= 5; //range: 0-7. Gain for amplifier 2

//FPGA states
parameter sRESET 	= 0; //Reset all internal variables. Make o_resetbAll=0.
parameter sPROGRAM	= 1; //Send programming bits to chip.
parameter sIDLE		= 2; //Do nothing.
//===========================================================================
//Input output declarations
input i_resetbFPGA; 		//resets FPGA
input i_ready;			//Alerts FPGA that chip is programmed and ready
input i_mainclk;		//Main clock
output reg o_resetbAll;		//Reset for the chip
output reg o_sclk;		//Serial clock for communication
output reg o_sdout;		//Serial data out from FPGA (to chip)


//Internal wire, reg declarations
reg [1:0] FPGAstate;		//Holds the state of FPGA
reg [3:0] count;		//Used for controlling sclk generation and transmission of serial data
reg mainclkby2, mainclkby4, mainclkby8, mainclkby16; //Low frequency clocks derived from mainclk

//=============================================================
//BEHAVIORAL DESCRIPTION
//=============================================================
// Setting the FPGA state
always @ (posedge(i_mainclk) or negedge(i_resetbFPGA))
begin
	if(i_resetbFPGA == 0)
		FPGAstate <= sRESET;
	else
	begin
		case(FPGAstate)
		sRESET: FPGAstate <= sPROGRAM;
		sPROGRAM: 
		begin	
			if(count== 10)
				FPGAstate <= sIDLE;
			else
				FPGAstate <= sPROGRAM;
		end
		sIDLE: FPGAstate <=sIDLE;
		default: FPGAstate <= sIDLE;
		endcase
	end
end
//========================================================
/*resetbALL
 * resetbAll=0, when FPGA is reset. 
 * resetbAll=1 at all other times.
*/
always @(posedge(i_mainclk) or negedge(i_resetbFPGA))
begin
	if(i_resetbFPGA == 0)
		o_resetbAll <= 0;
	else
	begin
		if(FPGAstate == sRESET)
			o_resetbAll <= 0;
		else
			o_resetbAll <= 1;
	end
end
//==========================================================
/* Generation of low frequency clocks from mainclk using divide-by-2 method
*/
always @ (posedge(i_mainclk) or negedge(i_resetbFPGA))
begin
	if(i_resetbFPGA == 0)
		mainclkby2 <= 0;
	else
		mainclkby2 <= ~mainclkby2;
end

always @ (posedge(mainclkby2) or negedge(i_resetbFPGA))
begin
	if(i_resetbFPGA == 0)
		mainclkby4 <= 0;
	else
		mainclkby4 <= ~mainclkby4;
end

always @(posedge(mainclkby4) or negedge(i_resetbFPGA))
begin
	if(i_resetbFPGA == 0)
		mainclkby8 <= 0;
	else
		mainclkby8 <= ~mainclkby8;
end

always @(posedge(mainclkby8) or negedge(i_resetbFPGA))
begin
	if(i_resetbFPGA == 0)
		mainclkby16 <= 0;
	else
		mainclkby16 <= ~mainclkby16;
end
//==========================================================
/*count
 * used for the generation of sclk and selecting the data to be sent in through sdin
 */
always	@(posedge(mainclkby16) or negedge(i_resetbFPGA))
begin
	if(i_resetbFPGA == 0)
		count <= 0;
	else
	begin
		if(FPGAstate == sPROGRAM)
		begin
			if(count == 11)
				count <= count;
			else
				count <= count+1;
		end
		else
			count <= count;
	end
end
//=========================================================
/*sclk
 * sclk is a clock only when the FPGA is programming the chip.
 */
always @ (posedge(mainclkby16) or negedge(i_resetbFPGA))
begin
	if(i_resetbFPGA == 0)
		o_sclk <= 1;
	else
	begin
		if(FPGAstate == sPROGRAM)
		begin
			if (count >= 1 && count <= 10)
				o_sclk <= ~o_sclk;
			else
				o_sclk <= 1;
		end
		else
			o_sclk <= 1;
	end
end

//=========================================================
/*sdin
 *serial data out from FPGA
 */
always @ (negedge(o_sclk) or negedge(i_resetbFPGA))
begin
	if(i_resetbFPGA == 0)
		o_sdout <= 0;
	else
	begin
		if(FPGAstate == sPROGRAM)
		begin
			case(count)
			4'd2: o_sdout <= opcode_gainA1[0];
			4'd4: o_sdout <= opcode_gainA1[1];
			4'd6: o_sdout <= opcode_gainA2[0];
			4'd8: o_sdout <= opcode_gainA2[1];
			4'd10: o_sdout <= opcode_gainA2[2];
			default: o_sdout <= o_sdout;
			endcase
		end
		else
			o_sdout <= 0;
		
	end
end
//==========================================================
endmodule

backend_tb.v
//File Name: Testbanch of FPGA
// Type: Module
// Department : Electrical engineering
// Author: Sagar
//Author's Email ID: guptasagar19965@gmail.com
// Purpose: BACKEND TEST
// Operation : TEST
// Date : 10 July 2023
// Testbanch module for the backend. This is has a module instantiation for
// the FPGA_model and the backend.
`timescale 1ns / 1ps
//==========================================================================
//Change the Verilog filenames approppriately.
`include "FPGA_model.v"
`include "backend.v"
//=========================================================================

module backend_tb();

reg resetbFPGA;
reg main_clk;

wire [1:0]gainA1 ; 
wire [2:0]gainA2 ;
wire resetbAll, resetb1, resetb2, resetbvco; 
wire vco_clk;
wire sclk, sdin;
wire ready;

//==========================================================================
//FPGA model instantiation
FPGA_model   FPGA_obj(	.i_resetbFPGA (resetbFPGA),
			.i_ready (ready),
			.o_resetbAll (resetbAll),
			.i_mainclk (main_clk),
			.o_sclk (sclk), 
			.o_sdout (sdin));

// Backend instantiation 
backend backend_obj (	.i_resetbAll (resetbAll),
			.i_clk (main_clk),
			.i_sclk (sclk),
			.i_sdin (sdin),
			.i_vco_clk (vco_clk),
			.o_ready (ready),
			.o_resetb1 (resetb1),
			.o_gainA1 (gainA1),
			.o_resetb2 (resetb2),
			.o_gainA2 (gainA2),
			.o_resetbvco (resetbvco)
			);
//============================================================================

//Test signal generation
initial
begin
	resetbFPGA <= 0;
	main_clk <= 0;
	
	#1 resetbFPGA <= 1;
	
end
initial
begin
     $dumpfile("Sagar.vcd");
     $dumpvars(0,backend_tb);
 end

//Generation of main_clk 
always #2.5 main_clk <= ~main_clk;
initial
 #6000 $finish;
//============================================================================
endmodule

Sagar.vcd
$date
	Thu Aug 24 23:44:33 2023
$end
$version
	Icarus Verilog
$end
$timescale
	1ps
$end
$scope module backend_tb $end
$var wire 1 ! vco_clk $end
$var wire 1 " sdin $end
$var wire 1 # sclk $end
$var wire 1 $ resetbvco $end
$var wire 1 % resetbAll $end
$var wire 1 & resetb2 $end
$var wire 1 ' resetb1 $end
$var wire 1 ( ready $end
$var wire 3 ) gainA2 [2:0] $end
$var wire 2 * gainA1 [1:0] $end
$var reg 1 + main_clk $end
$var reg 1 , resetbFPGA $end
$scope module FPGA_obj $end
$var wire 1 + i_mainclk $end
$var wire 1 , i_resetbFPGA $end
$var wire 1 ( i_ready $end
$var reg 2 - FPGAstate [1:0] $end
$var reg 4 . count [3:0] $end
$var reg 1 / mainclkby16 $end
$var reg 1 0 mainclkby2 $end
$var reg 1 1 mainclkby4 $end
$var reg 1 2 mainclkby8 $end
$var reg 1 % o_resetbAll $end
$var reg 1 # o_sclk $end
$var reg 1 " o_sdout $end
$upscope $end
$scope module backend_obj $end
$var wire 1 + i_clk $end
$var wire 1 % i_resetbAll $end
$var wire 1 # i_sclk $end
$var wire 1 " i_sdin $end
$var wire 1 ! i_vco_clk $end
$var reg 3 3 count [2:0] $end
$var reg 5 4 data [4:0] $end
$var reg 2 5 o_gainA1 [1:0] $end
$var reg 3 6 o_gainA2 [2:0] $end
$var reg 1 ( o_ready $end
$var reg 1 ' o_resetb1 $end
$var reg 1 & o_resetb2 $end
$var reg 1 $ o_resetbvco $end
$var reg 5 7 shift2 [4:0] $end
$var reg 5 8 shiftreg [4:0] $end
$var integer 32 9 i [31:0] $end
$upscope $end
$upscope $end
$enddefinitions $end
#0
$dumpvars
bx 9
b0 8
b0 7
b0 6
b0 5
b0 4
bx 3
02
01
00
0/
b0 .
b0 -
0,
0+
b0 *
b0 )
0(
0'
0&
0%
0$
1#
0"
z!
$end
#1000
1,
#2500
b1 .
1/
12
11
10
b1 -
b0 3
1+
#5000
0+
#7500
1%
00
1+
#10000
0+
#12500
01
10
b0 9
1+
#15000
0+
#17500
00
1+
#20000
0+
#22500
02
11
10
1+
#25000
0+
#27500
00
1+
#30000
0+
#32500
01
10
1+
#35000
0+
#37500
00
1+
#40000
0+
#42500
0/
12
11
10
1+
#45000
0+
#47500
00
1+
#50000
0+
#52500
01
10
1+
#55000
0+
#57500
00
1+
#60000
0+
#62500
02
11
10
1+
#65000
0+
#67500
00
1+
#70000
0+
#72500
01
10
1+
#75000
0+
#77500
00
1+
#80000
0+
#82500
1"
b10 .
0#
1/
12
11
10
1+
#85000
0+
#87500
00
1+
#90000
0+
#92500
01
10
1+
#95000
0+
#97500
00
1+
#100000
0+
#102500
02
11
10
1+
#105000
0+
#107500
00
1+
#110000
0+
#112500
01
10
1+
#115000
0+
#117500
00
1+
#120000
0+
#122500
0/
12
11
10
1+
#125000
0+
#127500
00
1+
#130000
0+
#132500
01
10
1+
#135000
0+
#137500
00
1+
#140000
0+
#142500
02
11
10
1+
#145000
0+
#147500
00
1+
#150000
0+
#152500
01
10
1+
#155000
0+
#157500
00
1+
#160000
0+
#162500
b1 3
b1 4
b10000 8
b1 9
1#
b11 .
1/
12
11
10
1+
#165000
0+
#167500
00
1+
#170000
0+
#172500
01
10
1+
#175000
0+
#177500
00
1+
#180000
0+
#182500
02
11
10
1+
#185000
0+
#187500
00
1+
#190000
0+
#192500
01
10
1+
#195000
0+
#197500
00
1+
#200000
0+
#202500
0/
12
11
10
1+
#205000
0+
#207500
00
1+
#210000
0+
#212500
01
10
1+
#215000
0+
#217500
00
1+
#220000
0+
#222500
02
11
10
1+
#225000
0+
#227500
00
1+
#230000
0+
#232500
01
10
1+
#235000
0+
#237500
00
1+
#240000
0+
#242500
0"
b100 .
0#
1/
12
11
10
1+
#245000
0+
#247500
00
1+
#250000
0+
#252500
01
10
1+
#255000
0+
#257500
00
1+
#260000
0+
#262500
02
11
10
1+
#265000
0+
#267500
00
1+
#270000
0+
#272500
01
10
1+
#275000
0+
#277500
00
1+
#280000
0+
#282500
0/
12
11
10
1+
#285000
0+
#287500
00
1+
#290000
0+
#292500
01
10
1+
#295000
0+
#297500
00
1+
#300000
0+
#302500
02
11
10
1+
#305000
0+
#307500
00
1+
#310000
0+
#312500
01
10
1+
#315000
0+
#317500
00
1+
#320000
0+
#322500
b0 4
b10 3
b10 9
b1000 8
b1000 7
1#
b101 .
1/
12
11
10
1+
#325000
0+
#327500
00
1+
#330000
0+
#332500
01
10
1+
#335000
0+
#337500
00
1+
#340000
0+
#342500
02
11
10
1+
#345000
0+
#347500
00
1+
#350000
0+
#352500
01
10
1+
#355000
0+
#357500
00
1+
#360000
0+
#362500
0/
12
11
10
1+
#365000
0+
#367500
00
1+
#370000
0+
#372500
01
10
1+
#375000
0+
#377500
00
1+
#380000
0+
#382500
02
11
10
1+
#385000
0+
#387500
00
1+
#390000
0+
#392500
01
10
1+
#395000
0+
#397500
00
1+
#400000
0+
#402500
1"
b110 .
0#
1/
12
11
10
1+
#405000
0+
#407500
00
1+
#410000
0+
#412500
01
10
1+
#415000
0+
#417500
00
1+
#420000
0+
#422500
02
11
10
1+
#425000
0+
#427500
00
1+
#430000
0+
#432500
01
10
1+
#435000
0+
#437500
00
1+
#440000
0+
#442500
0/
12
11
10
1+
#445000
0+
#447500
00
1+
#450000
0+
#452500
01
10
1+
#455000
0+
#457500
00
1+
#460000
0+
#462500
02
11
10
1+
#465000
0+
#467500
00
1+
#470000
0+
#472500
01
10
1+
#475000
0+
#477500
00
1+
#480000
0+
#482500
b11 3
b1 4
b10100 8
b100 7
b11 9
1#
b111 .
1/
12
11
10
1+
#485000
0+
#487500
00
1+
#490000
0+
#492500
01
10
1+
#495000
0+
#497500
00
1+
#500000
0+
#502500
02
11
10
1+
#505000
0+
#507500
00
1+
#510000
0+
#512500
01
10
1+
#515000
0+
#517500
00
1+
#520000
0+
#522500
0/
12
11
10
1+
#525000
0+
#527500
00
1+
#530000
0+
#532500
01
10
1+
#535000
0+
#537500
00
1+
#540000
0+
#542500
02
11
10
1+
#545000
0+
#547500
00
1+
#550000
0+
#552500
01
10
1+
#555000
0+
#557500
00
1+
#560000
0+
#562500
0"
b1000 .
0#
1/
12
11
10
1+
#565000
0+
#567500
00
1+
#570000
0+
#572500
01
10
1+
#575000
0+
#577500
00
1+
#580000
0+
#582500
02
11
10
1+
#585000
0+
#587500
00
1+
#590000
0+
#592500
01
10
1+
#595000
0+
#597500
00
1+
#600000
0+
#602500
0/
12
11
10
1+
#605000
0+
#607500
00
1+
#610000
0+
#612500
01
10
1+
#615000
0+
#617500
00
1+
#620000
0+
#622500
02
11
10
1+
#625000
0+
#627500
00
1+
#630000
0+
#632500
01
10
1+
#635000
0+
#637500
00
1+
#640000
0+
#642500
b0 4
b100 3
b100 9
b1010 8
b1010 7
1#
b1001 .
1/
12
11
10
1+
#645000
0+
#647500
00
1+
#650000
0+
#652500
01
10
1+
#655000
0+
#657500
00
1+
#660000
0+
#662500
02
11
10
1+
#665000
0+
#667500
00
1+
#670000
0+
#672500
01
10
1+
#675000
0+
#677500
00
1+
#680000
0+
#682500
0/
12
11
10
1+
#685000
0+
#687500
00
1+
#690000
0+
#692500
01
10
1+
#695000
0+
#697500
00
1+
#700000
0+
#702500
02
11
10
1+
#705000
0+
#707500
00
1+
#710000
0+
#712500
01
10
1+
#715000
0+
#717500
00
1+
#720000
0+
#722500
1"
b1010 .
0#
1/
12
11
10
1+
#725000
0+
#727500
b10 -
00
1+
#730000
0+
#732500
01
10
1+
#735000
0+
#737500
00
1+
#740000
0+
#742500
02
11
10
1+
#745000
0+
#747500
00
1+
#750000
0+
#752500
01
10
1+
#755000
0+
#757500
00
1+
#760000
0+
#762500
0/
12
11
10
1+
#765000
0+
#767500
00
1+
#770000
0+
#772500
01
10
1+
#775000
0+
#777500
00
1+
#780000
0+
#782500
02
11
10
1+
#785000
0+
#787500
00
1+
#790000
0+
#792500
01
10
1+
#795000
0+
#797500
00
1+
#800000
0+
#802500
b101 )
b101 6
b1 *
b1 5
b101 3
b1 4
b10101 8
b101 7
b101 9
1#
1/
12
11
10
1+
#805000
0+
#807500
00
1+
#810000
0+
#812500
01
10
1$
1+
#815000
0+
#817500
00
1+
#820000
0+
#822500
02
11
10
1+
#825000
0+
#827500
00
1+
#830000
0+
#832500
01
10
1+
#835000
0+
#837500
00
1+
#840000
0+
#842500
0/
12
11
10
1+
#845000
0+
#847500
00
1+
#850000
0+
#852500
01
10
1+
#855000
0+
#857500
00
1+
#860000
0+
#862500
02
11
10
1&
1'
1+
#865000
0+
#867500
00
1+
#870000
0+
#872500
01
10
1+
#875000
0+
#877500
00
1+
#880000
0+
#882500
1/
12
11
10
1+
#885000
0+
#887500
00
1+
#890000
0+
#892500
01
10
1+
#895000
0+
#897500
00
1+
#900000
0+
#902500
02
11
10
1+
#905000
0+
#907500
00
1+
#910000
0+
#912500
01
10
1(
1+
#915000
0+
#917500
00
b0 9
1+
#920000
0+
#922500
0/
12
11
10
1+
#925000
0+
#927500
00
1+
#930000
0+
#932500
01
10
1+
#935000
0+
#937500
00
1+
#940000
0+
#942500
02
11
10
1+
#945000
0+
#947500
00
1+
#950000
0+
#952500
01
10
1+
#955000
0+
#957500
00
1+
#960000
0+
#962500
1/
12
11
10
1+
#965000
0+
#967500
00
1+
#970000
0+
#972500
01
10
1+
#975000
0+
#977500
00
1+
#980000
0+
#982500
02
11
10
1+
#985000
0+
#987500
00
1+
#990000
0+
#992500
01
10
1+
#995000
0+
#997500
00
1+
#1000000
0+
#1002500
0/
12
11
10
1+
#1005000
0+
#1007500
00
1+
#1010000
0+
#1012500
01
10
1+
#1015000
0+
#1017500
00
1+
#1020000
0+
#1022500
02
11
10
1+
#1025000
0+
#1027500
00
1+
#1030000
0+
#1032500
01
10
1+
#1035000
0+
#1037500
00
1+
#1040000
0+
#1042500
1/
12
11
10
1+
#1045000
0+
#1047500
00
1+
#1050000
0+
#1052500
01
10
1+
#1055000
0+
#1057500
00
1+
#1060000
0+
#1062500
02
11
10
1+
#1065000
0+
#1067500
00
1+
#1070000
0+
#1072500
01
10
1+
#1075000
0+
#1077500
00
1+
#1080000
0+
#1082500
0/
12
11
10
1+
#1085000
0+
#1087500
00
1+
#1090000
0+
#1092500
01
10
1+
#1095000
0+
#1097500
00
1+
#1100000
0+
#1102500
02
11
10
1+
#1105000
0+
#1107500
00
1+
#1110000
0+
#1112500
01
10
1+
#1115000
0+
#1117500
00
1+
#1120000
0+
#1122500
1/
12
11
10
1+
#1125000
0+
#1127500
00
1+
#1130000
0+
#1132500
01
10
1+
#1135000
0+
#1137500
00
1+
#1140000
0+
#1142500
02
11
10
1+
#1145000
0+
#1147500
00
1+
#1150000
0+
#1152500
01
10
1+
#1155000
0+
#1157500
00
1+
#1160000
0+
#1162500
0/
12
11
10
1+
#1165000
0+
#1167500
00
1+
#1170000
0+
#1172500
01
10
1+
#1175000
0+
#1177500
00
1+
#1180000
0+
#1182500
02
11
10
1+
#1185000
0+
#1187500
00
1+
#1190000
0+
#1192500
01
10
1+
#1195000
0+
#1197500
00
1+
#1200000
0+
#1202500
1/
12
11
10
1+
#1205000
0+
#1207500
00
1+
#1210000
0+
#1212500
01
10
1+
#1215000
0+
#1217500
00
1+
#1220000
0+
#1222500
02
11
10
1+
#1225000
0+
#1227500
00
1+
#1230000
0+
#1232500
01
10
1+
#1235000
0+
#1237500
00
1+
#1240000
0+
#1242500
0/
12
11
10
1+
#1245000
0+
#1247500
00
1+
#1250000
0+
#1252500
01
10
1+
#1255000
0+
#1257500
00
1+
#1260000
0+
#1262500
02
11
10
1+
#1265000
0+
#1267500
00
1+
#1270000
0+
#1272500
01
10
1+
#1275000
0+
#1277500
00
1+
#1280000
0+
#1282500
1/
12
11
10
1+
#1285000
0+
#1287500
00
1+
#1290000
0+
#1292500
01
10
1+
#1295000
0+
#1297500
00
1+
#1300000
0+
#1302500
02
11
10
1+
#1305000
0+
#1307500
00
1+
#1310000
0+
#1312500
01
10
1+
#1315000
0+
#1317500
00
1+
#1320000
0+
#1322500
0/
12
11
10
1+
#1325000
0+
#1327500
00
1+
#1330000
0+
#1332500
01
10
1+
#1335000
0+
#1337500
00
1+
#1340000
0+
#1342500
02
11
10
1+
#1345000
0+
#1347500
00
1+
#1350000
0+
#1352500
01
10
1+
#1355000
0+
#1357500
00
1+
#1360000
0+
#1362500
1/
12
11
10
1+
#1365000
0+
#1367500
00
1+
#1370000
0+
#1372500
01
10
1+
#1375000
0+
#1377500
00
1+
#1380000
0+
#1382500
02
11
10
1+
#1385000
0+
#1387500
00
1+
#1390000
0+
#1392500
01
10
1+
#1395000
0+
#1397500
00
1+
#1400000
0+
#1402500
0/
12
11
10
1+
#1405000
0+
#1407500
00
1+
#1410000
0+
#1412500
01
10
1+
#1415000
0+
#1417500
00
1+
#1420000
0+
#1422500
02
11
10
1+
#1425000
0+
#1427500
00
1+
#1430000
0+
#1432500
01
10
1+
#1435000
0+
#1437500
00
1+
#1440000
0+
#1442500
1/
12
11
10
1+
#1445000
0+
#1447500
00
1+
#1450000
0+
#1452500
01
10
1+
#1455000
0+
#1457500
00
1+
#1460000
0+
#1462500
02
11
10
1+
#1465000
0+
#1467500
00
1+
#1470000
0+
#1472500
01
10
1+
#1475000
0+
#1477500
00
1+
#1480000
0+
#1482500
0/
12
11
10
1+
#1485000
0+
#1487500
00
1+
#1490000
0+
#1492500
01
10
1+
#1495000
0+
#1497500
00
1+
#1500000
0+
#1502500
02
11
10
1+
#1505000
0+
#1507500
00
1+
#1510000
0+
#1512500
01
10
1+
#1515000
0+
#1517500
00
1+
#1520000
0+
#1522500
1/
12
11
10
1+
#1525000
0+
#1527500
00
1+
#1530000
0+
#1532500
01
10
1+
#1535000
0+
#1537500
00
1+
#1540000
0+
#1542500
02
11
10
1+
#1545000
0+
#1547500
00
1+
#1550000
0+
#1552500
01
10
1+
#1555000
0+
#1557500
00
1+
#1560000
0+
#1562500
0/
12
11
10
1+
#1565000
0+
#1567500
00
1+
#1570000
0+
#1572500
01
10
1+
#1575000
0+
#1577500
00
1+
#1580000
0+
#1582500
02
11
10
1+
#1585000
0+
#1587500
00
1+
#1590000
0+
#1592500
01
10
1+
#1595000
0+
#1597500
00
1+
#1600000
0+
#1602500
1/
12
11
10
1+
#1605000
0+
#1607500
00
1+
#1610000
0+
#1612500
01
10
1+
#1615000
0+
#1617500
00
1+
#1620000
0+
#1622500
02
11
10
1+
#1625000
0+
#1627500
00
1+
#1630000
0+
#1632500
01
10
1+
#1635000
0+
#1637500
00
1+
#1640000
0+
#1642500
0/
12
11
10
1+
#1645000
0+
#1647500
00
1+
#1650000
0+
#1652500
01
10
1+
#1655000
0+
#1657500
00
1+
#1660000
0+
#1662500
02
11
10
1+
#1665000
0+
#1667500
00
1+
#1670000
0+
#1672500
01
10
1+
#1675000
0+
#1677500
00
1+
#1680000
0+
#1682500
1/
12
11
10
1+
#1685000
0+
#1687500
00
1+
#1690000
0+
#1692500
01
10
1+
#1695000
0+
#1697500
00
1+
#1700000
0+
#1702500
02
11
10
1+
#1705000
0+
#1707500
00
1+
#1710000
0+
#1712500
01
10
1+
#1715000
0+
#1717500
00
1+
#1720000
0+
#1722500
0/
12
11
10
1+
#1725000
0+
#1727500
00
1+
#1730000
0+
#1732500
01
10
1+
#1735000
0+
#1737500
00
1+
#1740000
0+
#1742500
02
11
10
1+
#1745000
0+
#1747500
00
1+
#1750000
0+
#1752500
01
10
1+
#1755000
0+
#1757500
00
1+
#1760000
0+
#1762500
1/
12
11
10
1+
#1765000
0+
#1767500
00
1+
#1770000
0+
#1772500
01
10
1+
#1775000
0+
#1777500
00
1+
#1780000
0+
#1782500
02
11
10
1+
#1785000
0+
#1787500
00
1+
#1790000
0+
#1792500
01
10
1+
#1795000
0+
#1797500
00
1+
#1800000
0+
#1802500
0/
12
11
10
1+
#1805000
0+
#1807500
00
1+
#1810000
0+
#1812500
01
10
1+
#1815000
0+
#1817500
00
1+
#1820000
0+
#1822500
02
11
10
1+
#1825000
0+
#1827500
00
1+
#1830000
0+
#1832500
01
10
1+
#1835000
0+
#1837500
00
1+
#1840000
0+
#1842500
1/
12
11
10
1+
#1845000
0+
#1847500
00
1+
#1850000
0+
#1852500
01
10
1+
#1855000
0+
#1857500
00
1+
#1860000
0+
#1862500
02
11
10
1+
#1865000
0+
#1867500
00
1+
#1870000
0+
#1872500
01
10
1+
#1875000
0+
#1877500
00
1+
#1880000
0+
#1882500
0/
12
11
10
1+
#1885000
0+
#1887500
00
1+
#1890000
0+
#1892500
01
10
1+
#1895000
0+
#1897500
00
1+
#1900000
0+
#1902500
02
11
10
1+
#1905000
0+
#1907500
00
1+
#1910000
0+
#1912500
01
10
1+
#1915000
0+
#1917500
00
1+
#1920000
0+
#1922500
1/
12
11
10
1+
#1925000
0+
#1927500
00
1+
#1930000
0+
#1932500
01
10
1+
#1935000
0+
#1937500
00
1+
#1940000
0+
#1942500
02
11
10
1+
#1945000
0+
#1947500
00
1+
#1950000
0+
#1952500
01
10
1+
#1955000
0+
#1957500
00
1+
#1960000
0+
#1962500
0/
12
11
10
1+
#1965000
0+
#1967500
00
1+
#1970000
0+
#1972500
01
10
1+
#1975000
0+
#1977500
00
1+
#1980000
0+
#1982500
02
11
10
1+
#1985000
0+
#1987500
00
1+
#1990000
0+
#1992500
01
10
1+
#1995000
0+
#1997500
00
1+
#2000000
0+
#2002500
1/
12
11
10
1+
#2005000
0+
#2007500
00
1+
#2010000
0+
#2012500
01
10
1+
#2015000
0+
#2017500
00
1+
#2020000
0+
#2022500
02
11
10
1+
#2025000
0+
#2027500
00
1+
#2030000
0+
#2032500
01
10
1+
#2035000
0+
#2037500
00
1+
#2040000
0+
#2042500
0/
12
11
10
1+
#2045000
0+
#2047500
00
1+
#2050000
0+
#2052500
01
10
1+
#2055000
0+
#2057500
00
1+
#2060000
0+
#2062500
02
11
10
1+
#2065000
0+
#2067500
00
1+
#2070000
0+
#2072500
01
10
1+
#2075000
0+
#2077500
00
1+
#2080000
0+
#2082500
1/
12
11
10
1+
#2085000
0+
#2087500
00
1+
#2090000
0+
#2092500
01
10
1+
#2095000
0+
#2097500
00
1+
#2100000
0+
#2102500
02
11
10
1+
#2105000
0+
#2107500
00
1+
#2110000
0+
#2112500
01
10
1+
#2115000
0+
#2117500
00
1+
#2120000
0+
#2122500
0/
12
11
10
1+
#2125000
0+
#2127500
00
1+
#2130000
0+
#2132500
01
10
1+
#2135000
0+
#2137500
00
1+
#2140000
0+
#2142500
02
11
10
1+
#2145000
0+
#2147500
00
1+
#2150000
0+
#2152500
01
10
1+
#2155000
0+
#2157500
00
1+
#2160000
0+
#2162500
1/
12
11
10
1+
#2165000
0+
#2167500
00
1+
#2170000
0+
#2172500
01
10
1+
#2175000
0+
#2177500
00
1+
#2180000
0+
#2182500
02
11
10
1+
#2185000
0+
#2187500
00
1+
#2190000
0+
#2192500
01
10
1+
#2195000
0+
#2197500
00
1+
#2200000
0+
#2202500
0/
12
11
10
1+
#2205000
0+
#2207500
00
1+
#2210000
0+
#2212500
01
10
1+
#2215000
0+
#2217500
00
1+
#2220000
0+
#2222500
02
11
10
1+
#2225000
0+
#2227500
00
1+
#2230000
0+
#2232500
01
10
1+
#2235000
0+
#2237500
00
1+
#2240000
0+
#2242500
1/
12
11
10
1+
#2245000
0+
#2247500
00
1+
#2250000
0+
#2252500
01
10
1+
#2255000
0+
#2257500
00
1+
#2260000
0+
#2262500
02
11
10
1+
#2265000
0+
#2267500
00
1+
#2270000
0+
#2272500
01
10
1+
#2275000
0+
#2277500
00
1+
#2280000
0+
#2282500
0/
12
11
10
1+
#2285000
0+
#2287500
00
1+
#2290000
0+
#2292500
01
10
1+
#2295000
0+
#2297500
00
1+
#2300000
0+
#2302500
02
11
10
1+
#2305000
0+
#2307500
00
1+
#2310000
0+
#2312500
01
10
1+
#2315000
0+
#2317500
00
1+
#2320000
0+
#2322500
1/
12
11
10
1+
#2325000
0+
#2327500
00
1+
#2330000
0+
#2332500
01
10
1+
#2335000
0+
#2337500
00
1+
#2340000
0+
#2342500
02
11
10
1+
#2345000
0+
#2347500
00
1+
#2350000
0+
#2352500
01
10
1+
#2355000
0+
#2357500
00
1+
#2360000
0+
#2362500
0/
12
11
10
1+
#2365000
0+
#2367500
00
1+
#2370000
0+
#2372500
01
10
1+
#2375000
0+
#2377500
00
1+
#2380000
0+
#2382500
02
11
10
1+
#2385000
0+
#2387500
00
1+
#2390000
0+
#2392500
01
10
1+
#2395000
0+
#2397500
00
1+
#2400000
0+
#2402500
1/
12
11
10
1+
#2405000
0+
#2407500
00
1+
#2410000
0+
#2412500
01
10
1+
#2415000
0+
#2417500
00
1+
#2420000
0+
#2422500
02
11
10
1+
#2425000
0+
#2427500
00
1+
#2430000
0+
#2432500
01
10
1+
#2435000
0+
#2437500
00
1+
#2440000
0+
#2442500
0/
12
11
10
1+
#2445000
0+
#2447500
00
1+
#2450000
0+
#2452500
01
10
1+
#2455000
0+
#2457500
00
1+
#2460000
0+
#2462500
02
11
10
1+
#2465000
0+
#2467500
00
1+
#2470000
0+
#2472500
01
10
1+
#2475000
0+
#2477500
00
1+
#2480000
0+
